ghedt/__init__.py
ghedt/coordinates.py
ghedt/design.py
ghedt/domains.py
ghedt/feature_recognition.py
ghedt/gfunction.py
ghedt/ground_heat_exchangers.py
ghedt/media.py
ghedt/search_routines.py
ghedt/utilities.py
ghedt/peak_load_analysis_tool/__init__.py
ghedt/peak_load_analysis_tool/borehole_heat_exchangers.py
ghedt/peak_load_analysis_tool/equivalance.py
ghedt/peak_load_analysis_tool/ground_loads.py
ghedt/peak_load_analysis_tool/media.py
ghedt/peak_load_analysis_tool/radial_numerical_borehole.py
tests/Atlanta_Office_Building_Loads.csv
tests/__init__.py
tests/test_bhe.py
tests/test_design.py
tests/test_ghe.py
tests/test_hyts.py
ghedt-0.3.1.dist-info/LICENSE
ghedt-0.3.1.dist-info/METADATA
ghedt-0.3.1.dist-info/WHEEL
ghedt-0.3.1.dist-info/top_level.txt
ghedt-0.3.1.dist-info/RECORD
