Metadata-Version: 2.1
Name: ghedt
Version: 0.3.1
Summary: A ground heat exchanger design tool with the advanced and unmatched capability of automatic borehole field selection based on drilling geometric land constraints.
Home-page: https://github.com/j-c-cook/ghedt
Author: Jack C. Cook
Author-email: jack-c-cook@protonmail.com
License: UNKNOWN
Download-URL: https://github.com/j-c-cook/ghedt/archive/v0.3.1.tar.gz
Platform: UNKNOWN
Requires-Dist: pygfunction (>=2.1)
Requires-Dist: pandas (>=1.3.2)
Requires-Dist: openpyxl (>=3.0.8)
Requires-Dist: opencv-python (==4.5.4.58)
